README.md
setup.py
datadaysolutions/__init__.py
datadaysolutions/solutions.py
datadaysolutions.egg-info/PKG-INFO
datadaysolutions.egg-info/SOURCES.txt
datadaysolutions.egg-info/dependency_links.txt
datadaysolutions.egg-info/not-zip-safe
datadaysolutions.egg-info/top_level.txt
datadaysolutions.egg-info/.ipynb_checkpoints/not-zip-safe-checkpoint