Metadata-Version: 1.0
Name: datadaysolutions
Version: 1.0.0
Summary: Answers, hints, and checks for Data Day excercises
Home-page: UNKNOWN
Author: Charlie Beacham
Author-email: charles.beacham@daimlertruck.com
License: UNKNOWN
Platform: UNKNOWN
